[{"line":1,"elements":[{"start_timestamp":"2023-10-08T12:26:21.466Z","before":[{"result":{"duration":1002000,"status":"passed"},"match":{"location":"stepDefinitions.Hooks.setUp(io.cucumber.java.Scenario)"}}],"line":3,"name":"Login with valid credentials","description":"","id":"login;login-with-valid-credentials","after":[{"result":{"status":"passed"},"match":{"location":"stepDefinitions.Hooks.tearDown(io.cucumber.java.Scenario)"}}],"type":"scenario","keyword":"Scenario","steps":[{"result":{"status":"passed"},"line":4,"name":"I navigate to the login page","match":{"location":"stepDefinitions.LoginSteps.iNavigateToTheLoginPage()"},"keyword":"Given "},{"result":{"status":"passed"},"line":5,"name":"I enter the username as admin and password as admin","match":{"location":"stepDefinitions.LoginSteps.iEnterTheUsernameAsAdminAndPasswordAsAdmin()"},"keyword":"And "},{"result":{"status":"passed"},"line":6,"name":"I click on the login button","match":{"location":"stepDefinitions.LoginSteps.iClickOnTheLoginButton()"},"keyword":"And "},{"result":{"duration":4000900,"status":"passed"},"line":7,"name":"I should see the userform page","match":{"location":"stepDefinitions.LoginSteps.iShouldSeeTheUserformPage()"},"keyword":"Then "}]}],"name":"Login","description":"    This feature deals with the login functionality of the applications","id":"login","keyword":"Feature","uri":"classpath:features/Login.feature","tags":[]}]